easyxlsx/__init__.py
easyxlsx/base.py
tests/__init__.py
tests/test_base.py
easyxlsx-0.3.11.dist-info/LICENSE
easyxlsx-0.3.11.dist-info/METADATA
easyxlsx-0.3.11.dist-info/WHEEL
easyxlsx-0.3.11.dist-info/top_level.txt
easyxlsx-0.3.11.dist-info/RECORD
