Metadata-Version: 2.1
Name: easyxlsx
Version: 0.3.11
Summary: easy way to use xlsxwriter.
Home-page: https://github.com/istommao/easyxlsx
Author: codingcat
Author-email: istommao@gmail.com
License: http://opensource.org/licenses/MIT
Platform: UNKNOWN
Requires-Dist: XlsxWriter (>=1.1.1)
